src/__init__.py
src/basic_solid_body.py
src/config.py
src/driver.py
src/element_menu.py
src/fixed.py
src/gas.py
src/grid.py
src/grid_object.py
src/liquid.py
src/main.py
src/painter.py
src/particle.py
src/particle_data.py
src/screen.py
src/solid.py
src/solid_body.py
src/solid_body_particle.py
src/start_menu.py
src/tool_menu.py
src/ufo_solid_body.py
sandcraft_anthonyvkane47-1.0.dist-info/LICENSE
sandcraft_anthonyvkane47-1.0.dist-info/METADATA
sandcraft_anthonyvkane47-1.0.dist-info/WHEEL
sandcraft_anthonyvkane47-1.0.dist-info/top_level.txt
sandcraft_anthonyvkane47-1.0.dist-info/RECORD
