Metadata-Version: 2.1
Name: sandcraft-anthonyvkane47
Version: 1.0
Summary: UNKNOWN
Home-page: https://github.com/jonathansessa/Sandcraft
Author: jsessa@ufl.edu
License: UNKNOWN
Platform: UNKNOWN
Requires-Python: <4,>=3.7
License-File: LICENSE
Requires-Dist: pygame (>=2.0)
